telluric/__init__.py
telluric/main.py
telluric_ai-0.1.0.dist-info/LICENSE
telluric_ai-0.1.0.dist-info/METADATA
telluric_ai-0.1.0.dist-info/WHEEL
telluric_ai-0.1.0.dist-info/entry_points.txt
telluric_ai-0.1.0.dist-info/top_level.txt
telluric_ai-0.1.0.dist-info/RECORD
