Metadata-Version: 2.1
Name: telluric-ai
Version: 0.1.0
Summary: A simple example Python project
Author-email: Your Name <your.email@example.com>
License: 
Keywords: example,tutorial,package
Classifier: Programming Language :: Python :: 3
Classifier: License :: OSI Approved :: MIT License
Classifier: Operating System :: OS Independent
Requires-Python: >=3.7
License-File: LICENSE
Requires-Dist: requests>=2.25.0
